picamzero/Camera.py
picamzero/PicameraZeroException.py
picamzero/__init__.py
picamzero/utilities.py
picamzero-1.0.1.dist-info/METADATA
picamzero-1.0.1.dist-info/WHEEL
picamzero-1.0.1.dist-info/licenses/LICENSE
picamzero-1.0.1.dist-info/RECORD
