Metadata-Version: 2.3
Name: picamzero
Version: 1.0.1
Summary: A library to make it easy for beginners to use the Raspberry Pi camera
Author-email: Raspberry Pi Foundation <learning@raspberrypi.org>
License: MIT License
License-File: LICENSE
Requires-Python: >=3.11
Requires-Dist: opencv-python-headless
Requires-Dist: picamera2
